vmut/__init__.py
vmut/icon.py
vmut/vms.py
vmu_tools-0.1.9.dist-info/LICENSE
vmu_tools-0.1.9.dist-info/METADATA
vmu_tools-0.1.9.dist-info/WHEEL
vmu_tools-0.1.9.dist-info/top_level.txt
vmu_tools-0.1.9.dist-info/RECORD
