Metadata-Version: 2.1
Name: vmu-tools
Version: 0.1.9
Summary: A set of tools for Dreamcast VMUcle icon
Home-page: https://github.com/slurmking/vmu-tools
Author: slurmking
License: UNKNOWN
Platform: UNKNOWN
Classifier: Programming Language :: Python :: 3.0
Classifier: Programming Language :: Python :: 3.9
Classifier: Topic :: Utilities
Classifier: License :: OSI Approved :: GNU General Public License v3 (GPLv3)
License-File: LICENSE
Requires-Dist: Pillow
